README.md
setup.py
minplus_algebra/__init__.py
minplus_algebra/curves.py
minplus_algebra/operators.py
minplus_algebra/operators_test.py
minplus_algebra.egg-info/PKG-INFO
minplus_algebra.egg-info/SOURCES.txt
minplus_algebra.egg-info/dependency_links.txt
minplus_algebra.egg-info/requires.txt
minplus_algebra.egg-info/top_level.txt